SpokeoAPI/__init__.py
SpokeoAPI/pyarmor_runtime_000000/__init__.py
SpokeoAPI/pyarmor_runtime_000000/pyarmor_runtime.pyd
spokeoapi-0.1.4.dist-info/METADATA
spokeoapi-0.1.4.dist-info/WHEEL
spokeoapi-0.1.4.dist-info/top_level.txt
spokeoapi-0.1.4.dist-info/RECORD
