Metadata-Version: 2.4
Name: SpokeoAPI
Version: 0.1.4
Summary: official API wrapper for Spokeo lookup service
Home-page: https://github.com/zhangxinxu
Author: Wei Zhang
Author-email: zhangwei.api@protonmail.com
Requires-Python: >=3.6
Requires-Dist: requests
Requires-Dist: tls_client
Dynamic: author
Dynamic: author-email
Dynamic: description
Dynamic: description-content-type
Dynamic: home-page
Dynamic: requires-dist
Dynamic: requires-python
Dynamic: summary
